[{"reasons": {"count": 0, "items": [{"summary": "This spot is popular", "type": "general", "reasonName": "globalInteractionReason"}]}, "venue": {"id": "5324a973498e4a9ae2e3bc77", "name": "Chloe's Restaurant and Lounge", "location": {"address": "9413 Avenue L", "lat": 40.63756855213085, "lng": -73.89736790698011, "labeledLatLngs": [{"label": "display", "lat": 40.63756855213085, "lng": -73.89736790698011}], "distance": 457, "postalCode": "11236", "cc": "US", "city": "Brooklyn", "state": "NY", "country": "United States", "formattedAddress": ["9413 Avenue L", "Brooklyn, NY 11236", "United States"]}, "categories": [{"id": "4bf58dd8d48988d144941735", "name": "Caribbean Restaurant", "pluralName": "Caribbean Restaurants", "shortName": "Caribbean", "icon": {"prefix": "https://ss3.4sqi.net/img/categories_v2/food/caribbean_", "suffix": ".png"}, "primary": true}], "photos": {"count": 0, "groups": []}}, "referralId": "e-0-5324a973498e4a9ae2e3bc77-0"}, {"reasons": {"count": 0, "items": [{"summary": "This spot is popular", "type": "general", "reasonName": "globalInteractionReason"}]}, "venue": {"id": "4bf49b526a31d13a0608962e", "name": "Double Dragon Chinese Food", "location": {"address": "8712 Avenue L", "crossStreet": "E 87th Street", "lat": 40.633959000000004, "lng": -73.902186, "labeledLatLngs": [{"label": "display", "lat": 40.633959000000004, "lng": -73.902186}, {"label": "entrance", "lat": 40.634029, "lng": -73.902266}], "distance": 178, "postalCode": "11236", "cc": "US", "city": "Brooklyn", "state": "NY", "country": "United States", "formattedAddress": ["8712 Avenue L (E 87th Street)", "Brooklyn, NY 11236", "United States"]}, "categories": [{"id": "4bf58dd8d48988d142941735", "name": "Asian Restaurant", "pluralName": "Asian Restaurants", "shortName": "Asian", "icon": {"prefix": "https://ss3.4sqi.net/img/categories_v2/food/asian_", "suffix": ".png"}, "primary": true}], "photos": {"count": 0, "groups": []}}, "referralId": "e-0-4bf49b526a31d13a0608962e-1"}, {"reasons": {"count": 0, "items": [{"summary": "This spot is popular", "type": "general", "reasonName": "globalInteractionReason"}]}, "venue": {"id": "4d4dadd04aa3a093c4c145ae", "name": "Yi Hong", "location": {"address": "9103 Avenue L", "crossStreet": "E 91st ST", "lat": 40.636047, "lng": -73.899772, "labeledLatLngs": [{"label": "display", "lat": 40.636047, "lng": -73.899772}, {"label": "entrance", "lat": 40.635991, "lng": -73.89968}], "distance": 203, "postalCode": "11236", "cc": "US", "city": "Brooklyn", "state": "NY", "country": "United States", "formattedAddress": ["9103 Avenue L (E 91st ST)", "Brooklyn, NY 11236", "United States"]}, "categories": [{"id": "4bf58dd8d48988d145941735", "name": "Chinese Restaurant", "pluralName": "Chinese Restaurants", "shortName": "Chinese", "icon": {"prefix": "https://ss3.4sqi.net/img/categories_v2/food/asian_", "suffix": ".png"}, "primary": true}], "photos": {"count": 0, "groups": []}}, "referralId": "e-0-4d4dadd04aa3a093c4c145ae-2"}, {"reasons": {"count": 0, "items": [{"summary": "This spot is popular", "type": "general", "reasonName": "globalInteractionReason"}]}, "venue": {"id": "4cc87ad24650a35d1be3881e", "name": "Canarsie Fil-Am Store", "location": {"address": "9122 Avenue L", "lat": 40.636033000000005, "lng": -73.899033, "labeledLatLngs": [{"label": "display", "lat": 40.636033000000005, "lng": -73.899033}, {"label": "entrance", "lat": 40.636072, "lng": -73.899097}], "distance": 263, "postalCode": "11236", "cc": "US", "city": "Brooklyn", "state": "NY", "country": "United States", "formattedAddress": ["9122 Avenue L", "Brooklyn, NY 11236", "United States"]}, "categories": [{"id": "4bf58dd8d48988d118951735", "name": "Grocery Store", "pluralName": "Grocery Stores", "shortName": "Grocery Store", "icon": {"prefix": "https://ss3.4sqi.net/img/categories_v2/shops/food_grocery_", "suffix": ".png"}, "primary": true}], "photos": {"count": 0, "groups": []}}, "referralId": "e-0-4cc87ad24650a35d1be3881e-3"}, {"reasons": {"count": 0, "items": [{"summary": "This spot is popular", "type": "general", "reasonName": "globalInteractionReason"}]}, "venue": {"id": "565a7c95498ea94a28c960eb", "name": "Lavender Maids Cleaning Service", "location": {"address": "1554 Remsen Ave", "lat": 40.633227000000005, "lng": -73.89856, "labeledLatLngs": [{"label": "display", "lat": 40.633227000000005, "lng": -73.89856}, {"label": "entrance", "lat": 40.633268, "lng": -73.898495}], "distance": 395, "postalCode": "11236", "cc": "US", "city": "Brooklyn", "state": "NY", "country": "United States", "formattedAddress": ["1554 Remsen Ave", "Brooklyn, NY 11236", "United States"]}, "categories": [{"id": "545419b1498ea6ccd0202f58", "name": "Home Service", "pluralName": "Home Services & Repairs", "shortName": "Home Services", "icon": {"prefix": "https://ss3.4sqi.net/img/categories_v2/shops/hardware_", "suffix": ".png"}, "primary": true}], "photos": {"count": 0, "groups": []}}, "referralId": "e-0-565a7c95498ea94a28c960eb-4"}, {"reasons": {"count": 0, "items": [{"summary": "This spot is popular", "type": "general", "reasonName": "globalInteractionReason"}]}, "venue": {"id": "55031692498e03d3c9aff5cb", "name": "Maven Stores", "location": {"address": "1342 E 84th St", "lat": 40.631721151806126, "lng": -73.90384912490845, "labeledLatLngs": [{"label": "display", "lat": 40.631721151806126, "lng": -73.90384912490845}], "distance": 452, "postalCode": "11236", "cc": "US", "city": "Brooklyn", "state": "NY", "country": "United States", "formattedAddress": ["1342 E 84th St", "Brooklyn, NY 11236", "United States"]}, "categories": [{"id": "52f2ab2ebcbc57f1066b8b36", "name": "IT Services", "pluralName": "IT Services", "shortName": "IT Services", "icon": {"prefix": "https://ss3.4sqi.net/img/categories_v2/shops/technology_", "suffix": ".png"}, "primary": true}], "photos": {"count": 0, "groups": []}}, "referralId": "e-0-55031692498e03d3c9aff5cb-5"}, {"reasons": {"count": 0, "items": [{"summary": "This spot is popular", "type": "general", "reasonName": "globalInteractionReason"}]}, "venue": {"id": "4bae4b7cf964a520c49e3be3", "name": "Paerdegat Gym", "location": {"address": "Paerdegat ave n", "lat": 40.63344387893077, "lng": -73.90673241117949, "labeledLatLngs": [{"label": "display", "lat": 40.63344387893077, "lng": -73.90673241117949}], "distance": 457, "cc": "US", "city": "Brooklyn", "state": "NY", "country": "United States", "formattedAddress": ["Paerdegat ave n", "Brooklyn, NY", "United States"]}, "categories": [{"id": "4bf58dd8d48988d176941735", "name": "Gym", "pluralName": "Gyms", "shortName": "Gym", "icon": {"prefix": "https://ss3.4sqi.net/img/categories_v2/building/gym_", "suffix": ".png"}, "primary": true}], "photos": {"count": 0, "groups": []}}, "referralId": "e-0-4bae4b7cf964a520c49e3be3-6"}, {"reasons": {"count": 0, "items": [{"summary": "This spot is popular", "type": "general", "reasonName": "globalInteractionReason"}]}, "venue": {"id": "4bd613ebcfa7b71326fe26da", "name": "Lin Wang", "location": {"address": "9417 Avenue L", "lat": 40.637561, "lng": -73.897199, "labeledLatLngs": [{"label": "display", "lat": 40.637561, "lng": -73.897199}, {"label": "entrance", "lat": 40.637601, "lng": -73.897184}], "distance": 469, "postalCode": "11236", "cc": "US", "city": "Brooklyn", "state": "NY", "country": "United States", "formattedAddress": ["9417 Avenue L", "Brooklyn, NY 11236", "United States"]}, "categories": [{"id": "4bf58dd8d48988d149941735", "name": "Thai Restaurant", "pluralName": "Thai Restaurants", "shortName": "Thai", "icon": {"prefix": "https://ss3.4sqi.net/img/categories_v2/food/thai_", "suffix": ".png"}, "primary": true}], "delivery": {"id": "1067902", "url": "https://www.seamless.com/menu/new-lin-wang-9417-avenue-l-brooklyn/1067902?affiliate=1131&utm_source=foursquare-affiliate-network&utm_medium=affiliate&utm_campaign=1131&utm_content=1067902", "provider": {"name": "seamless", "icon": {"prefix": "https://fastly.4sqi.net/img/general/cap/", "sizes": [40, 50], "name": "/delivery_provider_seamless_20180129.png"}}}, "photos": {"count": 0, "groups": []}}, "referralId": "e-0-4bd613ebcfa7b71326fe26da-7"}]