[{"reasons": {"count": 0, "items": [{"summary": "This spot is popular", "type": "general", "reasonName": "globalInteractionReason"}]}, "venue": {"id": "4dc93ced45dd7809f94f0a07", "name": "Queens Side Of Whitestone SCEMS post", "location": {"lat": 40.79046789197476, "lng": -73.82360444592386, "labeledLatLngs": [{"label": "display", "lat": 40.79046789197476, "lng": -73.82360444592386}], "distance": 259, "cc": "US", "city": "New York", "state": "NY", "country": "United States", "formattedAddress": ["New York, NY", "United States"]}, "categories": [{"id": "4d954b16a243a5684b65b473", "name": "Rest Area", "pluralName": "Rest Areas", "shortName": "Rest Areas", "icon": {"prefix": "https://ss3.4sqi.net/img/categories_v2/travel/restarea_", "suffix": ".png"}, "primary": true}], "photos": {"count": 0, "groups": []}}, "referralId": "e-0-4dc93ced45dd7809f94f0a07-0"}, {"reasons": {"count": 0, "items": [{"summary": "This spot is popular", "type": "general", "reasonName": "globalInteractionReason"}]}, "venue": {"id": "57a22d36498e861f29dc6e1d", "name": "Clean Table", "location": {"address": "28 7th Ave", "crossStreet": "Leroy Street", "lat": 40.79166, "lng": -73.828467, "labeledLatLngs": [{"label": "display", "lat": 40.79166, "lng": -73.828467}, {"label": "entrance", "lat": 40.791604, "lng": -73.828422}], "distance": 191, "postalCode": "10011", "cc": "US", "city": "New York", "state": "NY", "country": "United States", "formattedAddress": ["28 7th Ave (Leroy Street)", "New York, NY 10011", "United States"]}, "categories": [{"id": "4bf58dd8d48988d1d3941735", "name": "Vegetarian / Vegan Restaurant", "pluralName": "Vegetarian / Vegan Restaurants", "shortName": "Vegetarian / Vegan", "icon": {"prefix": "https://ss3.4sqi.net/img/categories_v2/food/vegetarian_", "suffix": ".png"}, "primary": true}], "photos": {"count": 0, "groups": []}}, "referralId": "e-0-57a22d36498e861f29dc6e1d-1"}, {"reasons": {"count": 0, "items": [{"summary": "This spot is popular", "type": "general", "reasonName": "globalInteractionReason"}]}, "venue": {"id": "4e6eea91d22de80163664373", "name": "Tennis", "location": {"lat": 40.79291538816812, "lng": -73.82672906946324, "labeledLatLngs": [{"label": "display", "lat": 40.79291538816812, "lng": -73.82672906946324}], "distance": 257, "cc": "US", "state": "New York", "country": "United States", "formattedAddress": ["New York", "United States"]}, "categories": [{"id": "4e39a956bd410d7aed40cbc3", "name": "Tennis Court", "pluralName": "Tennis Courts", "shortName": "Tennis Court", "icon": {"prefix": "https://ss3.4sqi.net/img/categories_v2/arts_entertainment/stadium_tennis_", "suffix": ".png"}, "primary": true}], "photos": {"count": 0, "groups": []}}, "referralId": "e-0-4e6eea91d22de80163664373-2"}, {"reasons": {"count": 0, "items": [{"summary": "This spot is popular", "type": "general", "reasonName": "globalInteractionReason"}]}, "venue": {"id": "4e5534a0d4c0fe034283d665", "name": "El Ranchito de Daisy #2", "location": {"address": "10-08 Clintonville St", "lat": 40.79253990448924, "lng": -73.82373081033275, "labeledLatLngs": [{"label": "display", "lat": 40.79253990448924, "lng": -73.82373081033275}], "distance": 328, "postalCode": "11357", "cc": "US", "city": "Whitestone", "state": "NY", "country": "United States", "formattedAddress": ["10-08 Clintonville St", "Whitestone, NY 11357", "United States"]}, "categories": [{"id": "4bf58dd8d48988d1be941735", "name": "Latin American Restaurant", "pluralName": "Latin American Restaurants", "shortName": "Latin American", "icon": {"prefix": "https://ss3.4sqi.net/img/categories_v2/food/latinamerican_", "suffix": ".png"}, "primary": true}], "photos": {"count": 0, "groups": []}}, "referralId": "e-0-4e5534a0d4c0fe034283d665-3"}, {"reasons": {"count": 0, "items": [{"summary": "This spot is popular", "type": "general", "reasonName": "globalInteractionReason"}]}, "venue": {"id": "4cdbeea9fc973704740ed205", "name": "under the bridge downtown", "location": {"lat": 40.7893177544543, "lng": -73.82280030688706, "labeledLatLngs": [{"label": "display", "lat": 40.7893177544543, "lng": -73.82280030688706}], "distance": 356, "postalCode": "11354", "cc": "US", "city": "Whitestone", "state": "NY", "country": "United States", "formattedAddress": ["Whitestone, NY 11354", "United States"]}, "categories": [{"id": "4bf58dd8d48988d1e9931735", "name": "Rock Club", "pluralName": "Rock Clubs", "shortName": "Rock Club", "icon": {"prefix": "https://ss3.4sqi.net/img/categories_v2/arts_entertainment/musicvenue_rockclub_", "suffix": ".png"}, "primary": true}], "photos": {"count": 0, "groups": []}}, "referralId": "e-0-4cdbeea9fc973704740ed205-4"}]