[{"reasons": {"count": 0, "items": [{"summary": "This spot is popular", "type": "general", "reasonName": "globalInteractionReason"}]}, "venue": {"id": "4b660358f964a520560e2be3", "name": "Mill Basin Kosher Deli", "location": {"address": "5823 Avenue T", "crossStreet": "E 59th St", "lat": 40.6156428997584, "lng": -73.91811660417666, "labeledLatLngs": [{"label": "display", "lat": 40.6156428997584, "lng": -73.91811660417666}, {"label": "entrance", "lat": 40.615715, "lng": -73.91803}], "distance": 253, "postalCode": "11234", "cc": "US", "city": "Brooklyn", "state": "NY", "country": "United States", "formattedAddress": ["5823 Avenue T (E 59th St)", "Brooklyn, NY 11234", "United States"]}, "categories": [{"id": "4bf58dd8d48988d146941735", "name": "Deli / Bodega", "pluralName": "Delis / Bodegas", "shortName": "Deli / Bodega", "icon": {"prefix": "https://ss3.4sqi.net/img/categories_v2/food/deli_", "suffix": ".png"}, "primary": true}], "photos": {"count": 0, "groups": []}}, "referralId": "e-0-4b660358f964a520560e2be3-0"}, {"reasons": {"count": 0, "items": [{"summary": "This spot is popular", "type": "general", "reasonName": "globalInteractionReason"}]}, "venue": {"id": "4bdf45b90ee3a5932a9433b0", "name": "Pizza D' Amore", "location": {"address": "2147 Mill Ave", "lat": 40.614757439632704, "lng": -73.91270423925742, "labeledLatLngs": [{"label": "display", "lat": 40.614757439632704, "lng": -73.91270423925742}, {"label": "entrance", "lat": 40.614643, "lng": -73.912769}], "distance": 247, "postalCode": "11234", "cc": "US", "city": "Brooklyn", "state": "NY", "country": "United States", "formattedAddress": ["2147 Mill Ave", "Brooklyn, NY 11234", "United States"]}, "categories": [{"id": "4bf58dd8d48988d1ca941735", "name": "Pizza Place", "pluralName": "Pizza Places", "shortName": "Pizza", "icon": {"prefix": "https://ss3.4sqi.net/img/categories_v2/food/pizza_", "suffix": ".png"}, "primary": true}], "delivery": {"id": "284158", "url": "https://www.seamless.com/menu/pizza-damore-2147-mill-ave-brooklyn/284158?affiliate=1131&utm_source=foursquare-affiliate-network&utm_medium=affiliate&utm_campaign=1131&utm_content=284158", "provider": {"name": "seamless", "icon": {"prefix": "https://fastly.4sqi.net/img/general/cap/", "sizes": [40, 50], "name": "/delivery_provider_seamless_20180129.png"}}}, "photos": {"count": 0, "groups": []}, "venuePage": {"id": "91556128"}}, "referralId": "e-0-4bdf45b90ee3a5932a9433b0-1"}, {"reasons": {"count": 0, "items": [{"summary": "This spot is popular", "type": "general", "reasonName": "globalInteractionReason"}]}, "venue": {"id": "4c0d278e7189c928a08fd6b6", "name": "Bagels Supreme", "location": {"address": "6220 Avenue U", "crossStreet": "at 63rd St.", "lat": 40.615584999999996, "lng": -73.913116, "labeledLatLngs": [{"label": "display", "lat": 40.615584999999996, "lng": -73.913116}, {"label": "entrance", "lat": 40.615659, "lng": -73.91319}], "distance": 177, "postalCode": "11234", "cc": "US", "city": "Brooklyn", "state": "NY", "country": "United States", "formattedAddress": ["6220 Avenue U (at 63rd St.)", "Brooklyn, NY 11234", "United States"]}, "categories": [{"id": "4bf58dd8d48988d179941735", "name": "Bagel Shop", "pluralName": "Bagel Shops", "shortName": "Bagels", "icon": {"prefix": "https://ss3.4sqi.net/img/categories_v2/food/bagels_", "suffix": ".png"}, "primary": true}], "photos": {"count": 0, "groups": []}}, "referralId": "e-0-4c0d278e7189c928a08fd6b6-2"}, {"reasons": {"count": 0, "items": [{"summary": "This spot is popular", "type": "general", "reasonName": "globalInteractionReason"}]}, "venue": {"id": "4c019ee727dcc928bcdfe052", "name": "Dolly's Italian Ices", "location": {"address": "5805 Avenue T", "crossStreet": "at E 58th St", "lat": 40.615368314804705, "lng": -73.91844643386376, "labeledLatLngs": [{"label": "display", "lat": 40.615368314804705, "lng": -73.91844643386376}, {"label": "entrance", "lat": 40.615388, "lng": -73.918525}], "distance": 286, "postalCode": "11234", "cc": "US", "city": "Brooklyn", "state": "NY", "country": "United States", "formattedAddress": ["5805 Avenue T (at E 58th St)", "Brooklyn, NY 11234", "United States"]}, "categories": [{"id": "4bf58dd8d48988d1c9941735", "name": "Ice Cream Shop", "pluralName": "Ice Cream Shops", "shortName": "Ice Cream", "icon": {"prefix": "https://ss3.4sqi.net/img/categories_v2/food/icecream_", "suffix": ".png"}, "primary": true}], "photos": {"count": 0, "groups": []}}, "referralId": "e-0-4c019ee727dcc928bcdfe052-3"}, {"reasons": {"count": 0, "items": [{"summary": "This spot is popular", "type": "general", "reasonName": "globalInteractionReason"}]}, "venue": {"id": "4b193722f964a52056d923e3", "name": "La Villa Pizzeria", "location": {"address": "6610 Avenue U", "crossStreet": "at 66th St.", "lat": 40.616867412790334, "lng": -73.90985844032727, "labeledLatLngs": [{"label": "display", "lat": 40.616867412790334, "lng": -73.90985844032727}, {"label": "entrance", "lat": 40.61739, "lng": -73.909708}], "distance": 458, "postalCode": "11234", "cc": "US", "city": "Brooklyn", "state": "NY", "country": "United States", "formattedAddress": ["6610 Avenue U (at 66th St.)", "Brooklyn, NY 11234", "United States"]}, "categories": [{"id": "4bf58dd8d48988d1ca941735", "name": "Pizza Place", "pluralName": "Pizza Places", "shortName": "Pizza", "icon": {"prefix": "https://ss3.4sqi.net/img/categories_v2/food/pizza_", "suffix": ".png"}, "primary": true}], "photos": {"count": 0, "groups": []}, "venuePage": {"id": "124320465"}}, "referralId": "e-0-4b193722f964a52056d923e3-4"}, {"reasons": {"count": 0, "items": [{"summary": "This spot is popular", "type": "general", "reasonName": "globalInteractionReason"}]}, "venue": {"id": "4ba27a3af964a5208efc37e3", "name": "Gourmet Grill", "location": {"address": "6334 Avenue N", "lat": 40.61954308297777, "lng": -73.91611065315124, "labeledLatLngs": [{"label": "display", "lat": 40.61954308297777, "lng": -73.91611065315124}, {"label": "entrance", "lat": 40.619513, "lng": -73.916024}], "distance": 405, "postalCode": "11234", "cc": "US", "city": "Brooklyn", "state": "NY", "country": "United States", "formattedAddress": ["6334 Avenue N", "Brooklyn, NY 11234", "United States"]}, "categories": [{"id": "4bf58dd8d48988d14e941735", "name": "American Restaurant", "pluralName": "American Restaurants", "shortName": "American", "icon": {"prefix": "https://ss3.4sqi.net/img/categories_v2/food/default_", "suffix": ".png"}, "primary": true}], "delivery": {"id": "682827", "url": "https://www.seamless.com/menu/gourmet-grill-6334-avenue-n-brooklyn/682827?affiliate=1131&utm_source=foursquare-affiliate-network&utm_medium=affiliate&utm_campaign=1131&utm_content=682827", "provider": {"name": "seamless", "icon": {"prefix": "https://fastly.4sqi.net/img/general/cap/", "sizes": [40, 50], "name": "/delivery_provider_seamless_20180129.png"}}}, "photos": {"count": 0, "groups": []}}, "referralId": "e-0-4ba27a3af964a5208efc37e3-5"}, {"reasons": {"count": 0, "items": [{"summary": "This spot is popular", "type": "general", "reasonName": "globalInteractionReason"}]}, "venue": {"id": "4d7fc91f95c1a143260eecf2", "name": "Yoshi", "location": {"address": "Ave T", "crossStreet": "E. 59th St", "lat": 40.615668413926294, "lng": -73.91805552591212, "labeledLatLngs": [{"label": "display", "lat": 40.615668413926294, "lng": -73.91805552591212}], "distance": 247, "postalCode": "11234", "cc": "US", "city": "Brooklyn", "state": "NY", "country": "United States", "formattedAddress": ["Ave T (E. 59th St)", "Brooklyn, NY 11234", "United States"]}, "categories": [{"id": "4bf58dd8d48988d111941735", "name": "Japanese Restaurant", "pluralName": "Japanese Restaurants", "shortName": "Japanese", "icon": {"prefix": "https://ss3.4sqi.net/img/categories_v2/food/japanese_", "suffix": ".png"}, "primary": true}], "photos": {"count": 0, "groups": []}}, "referralId": "e-0-4d7fc91f95c1a143260eecf2-6"}, {"reasons": {"count": 0, "items": [{"summary": "This spot is popular", "type": "general", "reasonName": "globalInteractionReason"}]}, "venue": {"id": "4c267153b012b71350e30893", "name": "Landi's Pork Store", "location": {"address": "5909 Avenue N", "crossStreet": "Ralph Avenue", "lat": 40.61963309828226, "lng": -73.91791811535433, "labeledLatLngs": [{"label": "display", "lat": 40.61963309828226, "lng": -73.91791811535433}, {"label": "entrance", "lat": 40.619617, "lng": -73.917865}], "distance": 469, "postalCode": "11234", "cc": "US", "city": "Brooklyn", "state": "NY", "country": "United States", "formattedAddress": ["5909 Avenue N (Ralph Avenue)", "Brooklyn, NY 11234", "United States"]}, "categories": [{"id": "4bf58dd8d48988d110941735", "name": "Italian Restaurant", "pluralName": "Italian Restaurants", "shortName": "Italian", "icon": {"prefix": "https://ss3.4sqi.net/img/categories_v2/food/italian_", "suffix": ".png"}, "primary": true}], "photos": {"count": 0, "groups": []}}, "referralId": "e-0-4c267153b012b71350e30893-7"}, {"reasons": {"count": 0, "items": [{"summary": "This spot is popular", "type": "general", "reasonName": "globalInteractionReason"}]}, "venue": {"id": "53d2d280498eb383dd42ac1a", "name": "Hard Times Sundaes", "location": {"address": "5700 Avenue U", "crossStreet": "E. 58th St.", "lat": 40.612313, "lng": -73.91642, "labeledLatLngs": [{"label": "display", "lat": 40.612313, "lng": -73.91642}], "distance": 421, "postalCode": "11234", "cc": "US", "city": "Brooklyn", "state": "NY", "country": "United States", "formattedAddress": ["5700 Avenue U (E. 58th St.)", "Brooklyn, NY 11234", "United States"]}, "categories": [{"id": "4bf58dd8d48988d1cb941735", "name": "Food Truck", "pluralName": "Food Trucks", "shortName": "Food Truck", "icon": {"prefix": "https://ss3.4sqi.net/img/categories_v2/food/streetfood_", "suffix": ".png"}, "primary": true}], "photos": {"count": 0, "groups": []}}, "referralId": "e-0-53d2d280498eb383dd42ac1a-8"}, {"reasons": {"count": 0, "items": [{"summary": "This spot is popular", "type": "general", "reasonName": "globalInteractionReason"}]}, "venue": {"id": "5159c692011c2f97320edfdc", "name": "Frozen Planet Yogurt", "location": {"address": "6340 Avenue N", "lat": 40.61940426424289, "lng": -73.91589698935043, "labeledLatLngs": [{"label": "display", "lat": 40.61940426424289, "lng": -73.91589698935043}], "distance": 386, "postalCode": "11234", "cc": "US", "city": "Brooklyn", "state": "NY", "country": "United States", "formattedAddress": ["6340 Avenue N", "Brooklyn, NY 11234", "United States"]}, "categories": [{"id": "512e7cae91d4cbb4e5efe0af", "name": "Frozen Yogurt Shop", "pluralName": "Frozen Yogurt Shops", "shortName": "Yogurt", "icon": {"prefix": "https://ss3.4sqi.net/img/categories_v2/food/frozenyogurt_", "suffix": ".png"}, "primary": true}], "delivery": {"id": "697277", "url": "https://www.seamless.com/menu/frozen-planet-6340-avenue-n-brooklyn/697277?affiliate=1131&utm_source=foursquare-affiliate-network&utm_medium=affiliate&utm_campaign=1131&utm_content=697277", "provider": {"name": "seamless", "icon": {"prefix": "https://fastly.4sqi.net/img/general/cap/", "sizes": [40, 50], "name": "/delivery_provider_seamless_20180129.png"}}}, "photos": {"count": 0, "groups": []}, "venuePage": {"id": "52219312"}}, "referralId": "e-0-5159c692011c2f97320edfdc-9"}, {"reasons": {"count": 0, "items": [{"summary": "This spot is popular", "type": "general", "reasonName": "globalInteractionReason"}]}, "venue": {"id": "53cb315f498e5a7d7afbf60a", "name": "Lima Peruvian Restaurant", "location": {"address": "6620 Avenue U", "lat": 40.617069244384766, "lng": -73.9097671508789, "labeledLatLngs": [{"label": "display", "lat": 40.617069244384766, "lng": -73.9097671508789}], "distance": 471, "postalCode": "11234", "cc": "US", "city": "Brooklyn", "state": "NY", "country": "United States", "formattedAddress": ["6620 Avenue U", "Brooklyn, NY 11234", "United States"]}, "categories": [{"id": "4eb1bfa43b7b52c0e1adc2e8", "name": "Peruvian Restaurant", "pluralName": "Peruvian Restaurants", "shortName": "Peruvian", "icon": {"prefix": "https://ss3.4sqi.net/img/categories_v2/food/peruvian_", "suffix": ".png"}, "primary": true}], "delivery": {"id": "477317", "url": "https://www.seamless.com/menu/lima-restaurant-6620-ave-u-brooklyn/477317?affiliate=1131&utm_source=foursquare-affiliate-network&utm_medium=affiliate&utm_campaign=1131&utm_content=477317", "provider": {"name": "seamless", "icon": {"prefix": "https://fastly.4sqi.net/img/general/cap/", "sizes": [40, 50], "name": "/delivery_provider_seamless_20180129.png"}}}, "photos": {"count": 0, "groups": []}, "venuePage": {"id": "126661224"}}, "referralId": "e-0-53cb315f498e5a7d7afbf60a-10"}, {"reasons": {"count": 0, "items": [{"summary": "This spot is popular", "type": "general", "reasonName": "globalInteractionReason"}]}, "venue": {"id": "4d29a3ee342d6dcbe31905cb", "name": "Meats Supreme", "location": {"address": "6214 Avenue U", "crossStreet": "btwn Mill Av & E 63rd St", "lat": 40.61561708973933, "lng": -73.91324661444712, "labeledLatLngs": [{"label": "display", "lat": 40.61561708973933, "lng": -73.91324661444712}], "distance": 166, "postalCode": "11234", "cc": "US", "city": "Brooklyn", "state": "NY", "country": "United States", "formattedAddress": ["6214 Avenue U (btwn Mill Av & E 63rd St)", "Brooklyn, NY 11234", "United States"]}, "categories": [{"id": "4bf58dd8d48988d118951735", "name": "Grocery Store", "pluralName": "Grocery Stores", "shortName": "Grocery Store", "icon": {"prefix": "https://ss3.4sqi.net/img/categories_v2/shops/food_grocery_", "suffix": ".png"}, "primary": true}], "photos": {"count": 0, "groups": []}}, "referralId": "e-0-4d29a3ee342d6dcbe31905cb-11"}, {"reasons": {"count": 0, "items": [{"summary": "This spot is popular", "type": "general", "reasonName": "globalInteractionReason"}]}, "venue": {"id": "4ba625e1f964a5201c3739e3", "name": "Mill Basin Bagel Cafe", "location": {"address": "6319 Avenue N", "lat": 40.61982990000001, "lng": -73.916547, "labeledLatLngs": [{"label": "display", "lat": 40.61982990000001, "lng": -73.916547}, {"label": "entrance", "lat": 40.619801, "lng": -73.916497}], "distance": 445, "postalCode": "11234", "cc": "US", "city": "Brooklyn", "state": "NY", "country": "United States", "formattedAddress": ["6319 Avenue N", "Brooklyn, NY 11234", "United States"]}, "categories": [{"id": "4bf58dd8d48988d179941735", "name": "Bagel Shop", "pluralName": "Bagel Shops", "shortName": "Bagels", "icon": {"prefix": "https://ss3.4sqi.net/img/categories_v2/food/bagels_", "suffix": ".png"}, "primary": true}], "photos": {"count": 0, "groups": []}}, "referralId": "e-0-4ba625e1f964a5201c3739e3-12"}, {"reasons": {"count": 0, "items": [{"summary": "This spot is popular", "type": "general", "reasonName": "globalInteractionReason"}]}, "venue": {"id": "4fa01114771667127b8c59d3", "name": "Duet Bakery", "location": {"address": "6181 Strickland Ave", "lat": 40.613448, "lng": -73.912553, "labeledLatLngs": [{"label": "display", "lat": 40.613448, "lng": -73.912553}, {"label": "entrance", "lat": 40.613481, "lng": -73.912314}], "distance": 356, "postalCode": "11234", "cc": "US", "city": "Brooklyn", "state": "NY", "country": "United States", "formattedAddress": ["6181 Strickland Ave", "Brooklyn, NY 11234", "United States"]}, "categories": [{"id": "4bf58dd8d48988d16a941735", "name": "Bakery", "pluralName": "Bakeries", "shortName": "Bakery", "icon": {"prefix": "https://ss3.4sqi.net/img/categories_v2/food/bakery_", "suffix": ".png"}, "primary": true}], "photos": {"count": 0, "groups": []}}, "referralId": "e-0-4fa01114771667127b8c59d3-13"}, {"reasons": {"count": 0, "items": [{"summary": "This spot is popular", "type": "general", "reasonName": "globalInteractionReason"}]}, "venue": {"id": "4ba93734f964a520fe143ae3", "name": "Walgreens", "location": {"address": "5716 Avenue U", "lat": 40.613008264211935, "lng": -73.91669405640647, "labeledLatLngs": [{"label": "display", "lat": 40.613008264211935, "lng": -73.91669405640647}, {"label": "entrance", "lat": 40.613225, "lng": -73.916694}], "distance": 354, "postalCode": "11234", "cc": "US", "city": "Brooklyn", "state": "NY", "country": "United States", "formattedAddress": ["5716 Avenue U", "Brooklyn, NY 11234", "United States"]}, "categories": [{"id": "4bf58dd8d48988d10f951735", "name": "Pharmacy", "pluralName": "Pharmacies", "shortName": "Pharmacy", "icon": {"prefix": "https://ss3.4sqi.net/img/categories_v2/shops/pharmacy_", "suffix": ".png"}, "primary": true}], "photos": {"count": 0, "groups": []}}, "referralId": "e-0-4ba93734f964a520fe143ae3-14"}, {"reasons": {"count": 0, "items": [{"summary": "This spot is popular", "type": "general", "reasonName": "globalInteractionReason"}]}, "venue": {"id": "4c41d7d2d7fad13ad51d08da", "name": "Brooklyn Zoo & Aquarium", "location": {"address": "2377 Ralph Ave", "lat": 40.62011279940736, "lng": -73.91719342763187, "labeledLatLngs": [{"label": "display", "lat": 40.62011279940736, "lng": -73.91719342763187}, {"label": "entrance", "lat": 40.620086, "lng": -73.917135}], "distance": 491, "postalCode": "11234", "cc": "US", "city": "Brooklyn", "state": "NY", "country": "United States", "formattedAddress": ["2377 Ralph Ave", "Brooklyn, NY 11234", "United States"]}, "categories": [{"id": "4bf58dd8d48988d100951735", "name": "Pet Store", "pluralName": "Pet Stores", "shortName": "Pet Store", "icon": {"prefix": "https://ss3.4sqi.net/img/categories_v2/shops/pet_store_", "suffix": ".png"}, "primary": true}], "photos": {"count": 0, "groups": []}}, "referralId": "e-0-4c41d7d2d7fad13ad51d08da-15"}, {"reasons": {"count": 0, "items": [{"summary": "This spot is popular", "type": "general", "reasonName": "globalInteractionReason"}]}, "venue": {"id": "4d02a01b2f96f04df1e41254", "name": "Chase Bank", "location": {"address": "6510 Avenue U", "lat": 40.6170316, "lng": -73.9110618, "labeledLatLngs": [{"label": "display", "lat": 40.6170316, "lng": -73.9110618}, {"label": "entrance", "lat": 40.61705, "lng": -73.911084}], "distance": 365, "postalCode": "11234", "cc": "US", "city": "Brooklyn", "state": "NY", "country": "United States", "formattedAddress": ["6510 Avenue U", "Brooklyn, NY 11234", "United States"]}, "categories": [{"id": "4bf58dd8d48988d10a951735", "name": "Bank", "pluralName": "Banks", "shortName": "Bank", "icon": {"prefix": "https://ss3.4sqi.net/img/categories_v2/shops/financial_", "suffix": ".png"}, "primary": true}], "photos": {"count": 0, "groups": []}}, "referralId": "e-0-4d02a01b2f96f04df1e41254-16"}, {"reasons": {"count": 0, "items": [{"summary": "This spot is popular", "type": "general", "reasonName": "globalInteractionReason"}]}, "venue": {"id": "4ee01ae9f7903c92cd2e0c6a", "name": "ChinaTokyo", "location": {"address": "5908 Avenue N", "crossStreet": "btwn E 59th & Ralph Ave", "lat": 40.619431112293704, "lng": -73.9179403244233, "labeledLatLngs": [{"label": "display", "lat": 40.619431112293704, "lng": -73.9179403244233}, {"label": "entrance", "lat": 40.619395, "lng": -73.917926}], "distance": 451, "postalCode": "11234", "cc": "US", "city": "Brooklyn", "state": "NY", "country": "United States", "formattedAddress": ["5908 Avenue N (btwn E 59th & Ralph Ave)", "Brooklyn, NY 11234", "United States"]}, "categories": [{"id": "4bf58dd8d48988d145941735", "name": "Chinese Restaurant", "pluralName": "Chinese Restaurants", "shortName": "Chinese", "icon": {"prefix": "https://ss3.4sqi.net/img/categories_v2/food/asian_", "suffix": ".png"}, "primary": true}], "delivery": {"id": "268057", "url": "https://www.seamless.com/menu/china-tokyo-5908-ave-n-brooklyn/268057?affiliate=1131&utm_source=foursquare-affiliate-network&utm_medium=affiliate&utm_campaign=1131&utm_content=268057", "provider": {"name": "seamless", "icon": {"prefix": "https://fastly.4sqi.net/img/general/cap/", "sizes": [40, 50], "name": "/delivery_provider_seamless_20180129.png"}}}, "photos": {"count": 0, "groups": []}}, "referralId": "e-0-4ee01ae9f7903c92cd2e0c6a-17"}, {"reasons": {"count": 0, "items": [{"summary": "This spot is popular", "type": "general", "reasonName": "globalInteractionReason"}]}, "venue": {"id": "4bfc3f24b5cd2d7fc34931fb", "name": "Sosaku", "location": {"address": "6328 Avenue N", "crossStreet": "Ralph", "lat": 40.619384000000004, "lng": -73.91624300000001, "labeledLatLngs": [{"label": "display", "lat": 40.619384000000004, "lng": -73.91624300000001}, {"label": "entrance", "lat": 40.619499, "lng": -73.916235}], "distance": 390, "postalCode": "11234", "cc": "US", "city": "Brooklyn", "state": "NY", "country": "United States", "formattedAddress": ["6328 Avenue N (Ralph)", "Brooklyn, NY 11234", "United States"]}, "categories": [{"id": "4bf58dd8d48988d111941735", "name": "Japanese Restaurant", "pluralName": "Japanese Restaurants", "shortName": "Japanese", "icon": {"prefix": "https://ss3.4sqi.net/img/categories_v2/food/japanese_", "suffix": ".png"}, "primary": true}], "delivery": {"id": "279801", "url": "https://www.seamless.com/menu/sosaku-japanese-restaurant-6328-ave-n-brooklyn/279801?affiliate=1131&utm_source=foursquare-affiliate-network&utm_medium=affiliate&utm_campaign=1131&utm_content=279801", "provider": {"name": "seamless", "icon": {"prefix": "https://fastly.4sqi.net/img/general/cap/", "sizes": [40, 50], "name": "/delivery_provider_seamless_20180129.png"}}}, "photos": {"count": 0, "groups": []}}, "referralId": "e-0-4bfc3f24b5cd2d7fc34931fb-18"}, {"reasons": {"count": 0, "items": [{"summary": "This spot is popular", "type": "general", "reasonName": "globalInteractionReason"}]}, "venue": {"id": "4cb612031b0af04d1fefcd25", "name": "Chase Bank", "location": {"address": "2401 Ralph Ave", "lat": 40.619303, "lng": -73.916975, "labeledLatLngs": [{"label": "display", "lat": 40.619303, "lng": -73.916975}, {"label": "entrance", "lat": 40.619309, "lng": -73.917034}], "distance": 401, "postalCode": "11234", "cc": "US", "city": "Brooklyn", "state": "NY", "country": "United States", "formattedAddress": ["2401 Ralph Ave", "Brooklyn, NY 11234", "United States"]}, "categories": [{"id": "4bf58dd8d48988d10a951735", "name": "Bank", "pluralName": "Banks", "shortName": "Bank", "icon": {"prefix": "https://ss3.4sqi.net/img/categories_v2/shops/financial_", "suffix": ".png"}, "primary": true}], "photos": {"count": 0, "groups": []}}, "referralId": "e-0-4cb612031b0af04d1fefcd25-19"}, {"reasons": {"count": 0, "items": [{"summary": "This spot is popular", "type": "general", "reasonName": "globalInteractionReason"}]}, "venue": {"id": "4bba2eec98c7ef3bfbcd3202", "name": "Key Food", "location": {"address": "6620 Avenue U", "crossStreet": "at E 66th St.", "lat": 40.61726873951865, "lng": -73.90977648217026, "labeledLatLngs": [{"label": "display", "lat": 40.61726873951865, "lng": -73.90977648217026}, {"label": "entrance", "lat": 40.617456, "lng": -73.909606}], "distance": 476, "postalCode": "11234", "cc": "US", "city": "Brooklyn", "state": "NY", "country": "United States", "formattedAddress": ["6620 Avenue U (at E 66th St.)", "Brooklyn, NY 11234", "United States"]}, "categories": [{"id": "52f2ab2ebcbc57f1066b8b46", "name": "Supermarket", "pluralName": "Supermarkets", "shortName": "Supermarket", "icon": {"prefix": "https://ss3.4sqi.net/img/categories_v2/shops/food_grocery_", "suffix": ".png"}, "primary": true}], "photos": {"count": 0, "groups": []}}, "referralId": "e-0-4bba2eec98c7ef3bfbcd3202-20"}, {"reasons": {"count": 0, "items": [{"summary": "This spot is popular", "type": "general", "reasonName": "globalInteractionReason"}]}, "venue": {"id": "4e146b7d14951daa08aa144b", "name": "Dagan's Kosher Pizza", "location": {"address": "6187 Strickland Ave", "lat": 40.61367993333333, "lng": -73.91224671666667, "labeledLatLngs": [{"label": "display", "lat": 40.61367993333333, "lng": -73.91224671666667}, {"label": "entrance", "lat": 40.613596, "lng": -73.912261}], "distance": 354, "postalCode": "11234", "cc": "US", "city": "Brooklyn", "state": "NY", "country": "United States", "formattedAddress": ["6187 Strickland Ave", "Brooklyn, NY 11234", "United States"]}, "categories": [{"id": "4bf58dd8d48988d1ca941735", "name": "Pizza Place", "pluralName": "Pizza Places", "shortName": "Pizza", "icon": {"prefix": "https://ss3.4sqi.net/img/categories_v2/food/pizza_", "suffix": ".png"}, "primary": true}], "photos": {"count": 0, "groups": []}}, "referralId": "e-0-4e146b7d14951daa08aa144b-21"}, {"reasons": {"count": 0, "items": [{"summary": "This spot is popular", "type": "general", "reasonName": "globalInteractionReason"}]}, "venue": {"id": "4e25fae981300e926f446900", "name": "Empire Grill", "location": {"address": "6185 Strickland Ave", "lat": 40.613606805454474, "lng": -73.91227508811421, "labeledLatLngs": [{"label": "display", "lat": 40.613606805454474, "lng": -73.91227508811421}], "distance": 358, "postalCode": "11234", "cc": "US", "city": "Brooklyn", "state": "NY", "country": "United States", "formattedAddress": ["6185 Strickland Ave", "Brooklyn, NY 11234", "United States"]}, "categories": [{"id": "4bf58dd8d48988d115941735", "name": "Middle Eastern Restaurant", "pluralName": "Middle Eastern Restaurants", "shortName": "Middle Eastern", "icon": {"prefix": "https://ss3.4sqi.net/img/categories_v2/food/middleeastern_", "suffix": ".png"}, "primary": true}], "photos": {"count": 0, "groups": []}}, "referralId": "e-0-4e25fae981300e926f446900-22"}, {"reasons": {"count": 0, "items": [{"summary": "This spot is popular", "type": "general", "reasonName": "globalInteractionReason"}]}, "venue": {"id": "511198f8e4b0b2cd3314b5d8", "name": "Joseph Dream Burger", "location": {"address": "6185 Strickland Ave", "crossStreet": "Mill Avenue", "lat": 40.613602, "lng": -73.912175, "labeledLatLngs": [{"label": "display", "lat": 40.613602, "lng": -73.912175}], "distance": 364, "postalCode": "11234", "cc": "US", "city": "Brooklyn", "state": "NY", "country": "United States", "formattedAddress": ["6185 Strickland Ave (Mill Avenue)", "Brooklyn, NY 11234", "United States"]}, "categories": [{"id": "4bf58dd8d48988d16c941735", "name": "Burger Joint", "pluralName": "Burger Joints", "shortName": "Burgers", "icon": {"prefix": "https://ss3.4sqi.net/img/categories_v2/food/burger_", "suffix": ".png"}, "primary": true}], "photos": {"count": 0, "groups": []}}, "referralId": "e-0-511198f8e4b0b2cd3314b5d8-23"}, {"reasons": {"count": 0, "items": [{"summary": "This spot is popular", "type": "general", "reasonName": "globalInteractionReason"}]}, "venue": {"id": "4df4415cb0fb807158c56f55", "name": "Bill's Bar", "location": {"address": "6326 Avenue N", "lat": 40.61961111883627, "lng": -73.91634892189333, "labeledLatLngs": [{"label": "display", "lat": 40.61961111883627, "lng": -73.91634892189333}, {"label": "entrance", "lat": 40.619498, "lng": -73.916262}], "distance": 417, "postalCode": "11234", "cc": "US", "city": "Brooklyn", "state": "NY", "country": "United States", "formattedAddress": ["6326 Avenue N", "Brooklyn, NY 11234", "United States"]}, "categories": [{"id": "4bf58dd8d48988d11b941735", "name": "Pub", "pluralName": "Pubs", "shortName": "Pub", "icon": {"prefix": "https://ss3.4sqi.net/img/categories_v2/nightlife/pub_", "suffix": ".png"}, "primary": true}], "photos": {"count": 0, "groups": []}}, "referralId": "e-0-4df4415cb0fb807158c56f55-24"}, {"reasons": {"count": 0, "items": [{"summary": "This spot is popular", "type": "general", "reasonName": "globalInteractionReason"}]}, "venue": {"id": "4c486f76417b20a167e0e0a9", "name": "Nails By Susan", "location": {"address": "6325 Avenue N", "lat": 40.619611, "lng": -73.916249, "labeledLatLngs": [{"label": "display", "lat": 40.619611, "lng": -73.916249}], "distance": 415, "postalCode": "11234", "cc": "US", "city": "Brooklyn", "state": "NY", "country": "United States", "formattedAddress": ["6325 Avenue N", "Brooklyn, NY 11234", "United States"]}, "categories": [{"id": "4bf58dd8d48988d10c951735", "name": "Cosmetics Shop", "pluralName": "Cosmetics Shops", "shortName": "Cosmetics", "icon": {"prefix": "https://ss3.4sqi.net/img/categories_v2/shops/beauty_cosmetic_", "suffix": ".png"}, "primary": true}], "photos": {"count": 0, "groups": []}}, "referralId": "e-0-4c486f76417b20a167e0e0a9-25"}, {"reasons": {"count": 0, "items": [{"summary": "This spot is popular", "type": "general", "reasonName": "globalInteractionReason"}]}, "venue": {"id": "4e188f17183880768f424468", "name": "Sippy Sip", "location": {"address": "5916 Avenue N", "crossStreet": "Ralph Avenue", "lat": 40.619275, "lng": -73.917654, "labeledLatLngs": [{"label": "display", "lat": 40.619275, "lng": -73.917654}, {"label": "entrance", "lat": 40.619413, "lng": -73.917638}], "distance": 423, "postalCode": "11234", "cc": "US", "city": "Brooklyn", "state": "NY", "country": "United States", "formattedAddress": ["5916 Avenue N (Ralph Avenue)", "Brooklyn, NY 11234", "United States"]}, "categories": [{"id": "4bf58dd8d48988d186941735", "name": "Liquor Store", "pluralName": "Liquor Stores", "shortName": "Liquor Store", "icon": {"prefix": "https://ss3.4sqi.net/img/categories_v2/shops/food_liquor_", "suffix": ".png"}, "primary": true}], "photos": {"count": 0, "groups": []}}, "referralId": "e-0-4e188f17183880768f424468-26"}, {"reasons": {"count": 0, "items": [{"summary": "This spot is popular", "type": "general", "reasonName": "globalInteractionReason"}]}, "venue": {"id": "58b0be378cb34e443b4ad0f5", "name": "Brooklyn Diner", "location": {"lat": 40.619473, "lng": -73.91734, "labeledLatLngs": [{"label": "display", "lat": 40.619473, "lng": -73.91734}], "distance": 431, "postalCode": "11234", "cc": "US", "city": "Brooklyn", "state": "NY", "country": "United States", "formattedAddress": ["Brooklyn, NY 11234", "United States"]}, "categories": [{"id": "4bf58dd8d48988d147941735", "name": "Diner", "pluralName": "Diners", "shortName": "Diner", "icon": {"prefix": "https://ss3.4sqi.net/img/categories_v2/food/diner_", "suffix": ".png"}, "primary": true}], "photos": {"count": 0, "groups": []}}, "referralId": "e-0-58b0be378cb34e443b4ad0f5-27"}, {"reasons": {"count": 0, "items": [{"summary": "This spot is popular", "type": "general", "reasonName": "globalInteractionReason"}]}, "venue": {"id": "4e3ab3d17d8b90abc329b864", "name": "Seaview Jewelers", "location": {"address": "5902 Avenue N", "crossStreet": "East 59th Street", "lat": 40.619246000000004, "lng": -73.91809599999999, "labeledLatLngs": [{"label": "display", "lat": 40.619246000000004, "lng": -73.91809599999999}, {"label": "entrance", "lat": 40.619383, "lng": -73.918111}], "distance": 440, "postalCode": "11234", "cc": "US", "city": "Brooklyn", "state": "NY", "country": "United States", "formattedAddress": ["5902 Avenue N (East 59th Street)", "Brooklyn, NY 11234", "United States"]}, "categories": [{"id": "4bf58dd8d48988d111951735", "name": "Jewelry Store", "pluralName": "Jewelry Stores", "shortName": "Jewelry", "icon": {"prefix": "https://ss3.4sqi.net/img/categories_v2/shops/jewelry_", "suffix": ".png"}, "primary": true}], "photos": {"count": 0, "groups": []}, "venuePage": {"id": "67022910"}}, "referralId": "e-0-4e3ab3d17d8b90abc329b864-28"}, {"reasons": {"count": 0, "items": [{"summary": "This spot is popular", "type": "general", "reasonName": "globalInteractionReason"}]}, "venue": {"id": "4b5bbfb0f964a520021429e3", "name": "China Kettle", "location": {"address": "Avenue U", "crossStreet": "E 66th St", "lat": 40.61686733377776, "lng": -73.90996452539898, "labeledLatLngs": [{"label": "display", "lat": 40.61686733377776, "lng": -73.90996452539898}, {"label": "entrance", "lat": 40.617374, "lng": -73.909733}], "distance": 449, "postalCode": "11234", "cc": "US", "city": "Brooklyn", "state": "NY", "country": "United States", "formattedAddress": ["Avenue U (E 66th St)", "Brooklyn, NY 11234", "United States"]}, "categories": [{"id": "4bf58dd8d48988d145941735", "name": "Chinese Restaurant", "pluralName": "Chinese Restaurants", "shortName": "Chinese", "icon": {"prefix": "https://ss3.4sqi.net/img/categories_v2/food/asian_", "suffix": ".png"}, "primary": true}], "delivery": {"id": "307251", "url": "https://www.seamless.com/menu/china-kettle-6606-avenue-u-brooklyn/307251?affiliate=1131&utm_source=foursquare-affiliate-network&utm_medium=affiliate&utm_campaign=1131&utm_content=307251", "provider": {"name": "seamless", "icon": {"prefix": "https://fastly.4sqi.net/img/general/cap/", "sizes": [40, 50], "name": "/delivery_provider_seamless_20180129.png"}}}, "photos": {"count": 0, "groups": []}}, "referralId": "e-0-4b5bbfb0f964a520021429e3-29"}, {"reasons": {"count": 0, "items": [{"summary": "This spot is popular", "type": "general", "reasonName": "globalInteractionReason"}]}, "venue": {"id": "4e4d020fbd413c4cc66df2a9", "name": "Sushiyama", "location": {"address": "6612 Avenue U", "lat": 40.61692206966377, "lng": -73.90986355223251, "labeledLatLngs": [{"label": "display", "lat": 40.61692206966377, "lng": -73.90986355223251}], "distance": 459, "postalCode": "11234", "cc": "US", "city": "Brooklyn", "state": "NY", "country": "United States", "formattedAddress": ["6612 Avenue U", "Brooklyn, NY 11234", "United States"]}, "categories": [{"id": "4bf58dd8d48988d1d2941735", "name": "Sushi Restaurant", "pluralName": "Sushi Restaurants", "shortName": "Sushi", "icon": {"prefix": "https://ss3.4sqi.net/img/categories_v2/food/sushi_", "suffix": ".png"}, "primary": true}], "photos": {"count": 0, "groups": []}}, "referralId": "e-0-4e4d020fbd413c4cc66df2a9-30"}, {"reasons": {"count": 0, "items": [{"summary": "This spot is popular", "type": "general", "reasonName": "globalInteractionReason"}]}, "venue": {"id": "4ce4227ca3c6721e724414cf", "name": "Continental Barber Shop", "location": {"address": "5814 Avenue N", "crossStreet": "Btwn E. 58th & E. 59th", "lat": 40.6194342290836, "lng": -73.91878555119531, "labeledLatLngs": [{"label": "display", "lat": 40.6194342290836, "lng": -73.91878555119531}, {"label": "entrance", "lat": 40.619345, "lng": -73.918675}], "distance": 492, "postalCode": "11234", "cc": "US", "city": "Brooklyn", "state": "NY", "country": "United States", "formattedAddress": ["5814 Avenue N (Btwn E. 58th & E. 59th)", "Brooklyn, NY 11234", "United States"]}, "categories": [{"id": "4bf58dd8d48988d10c951735", "name": "Cosmetics Shop", "pluralName": "Cosmetics Shops", "shortName": "Cosmetics", "icon": {"prefix": "https://ss3.4sqi.net/img/categories_v2/shops/beauty_cosmetic_", "suffix": ".png"}, "primary": true}], "photos": {"count": 0, "groups": []}}, "referralId": "e-0-4ce4227ca3c6721e724414cf-31"}]